syusekikairo/report/src/main.v
module HalfAdder(iA, iB, oS, oC);
    input iA, iB;
    output oS, oC;
    assign oS = iA ^ iB;
    assign oC = iA & iB;
endmodule

module FullAdder(iA, iB, iCy, oS, oCy);
    input iA, iB, iCy;
    output oS, oCy;
    wire s1, c1, c2;
    HalfAdder HA1(.iA(iA), .iB(iB), .oS(s1), .oC(c1));
    HalfAdder HA2(.iA(s1), .iB(iCy), .oS(oS), .oC(c2));
    assign oCy = c1 | c2;
endmodule

module HalfSubtractor(iA, iB, oD, oB);
    input iA, iB;
    output oD, oB;
    assign oD = iA ^ iB;
    assign oB = ~iA & iB;
endmodule

module FullSubtractor(iA, iB, iBr, oD, oBr);
    input iA, iB, iBr;
    output oD, oBr;
    wire d1, b1, b2;
    HalfSubtractor HS1(.iA(iA), .iB(iB), .oD(d1), .oB(b1));
    HalfSubtractor HS2(.iA(d1), .iB(iBr), .oD(oD), .oB(b2));
    assign oBr = b1 | b2;
endmodule

module main(SW1, SW2, SW3, SW4, LD1, LD2);
    input SW1, SW2, SW3, SW4;
    output LD1, LD2;
    wire addS, addC;
    wire subD, subB;
    wire [1:0] addResult;
    wire [1:0] subResult;
    wire [1:0] muxResult;

    FullAdder FA(.iA(SW1), .iB(SW2), .iCy(SW3), .oS(addS), .oCy(addC));
    FullSubtractor FS(.iA(SW1), .iB(SW2), .iBr(SW3), .oD(subD), .oBr(subB));

    assign addResult = {addC, addS};
    assign subResult = {subB, subD};
    assign muxResult = SW4 ? subResult : addResult;
    assign {LD2, LD1} = ~muxResult;
endmodule

syusekikairo/report/src/simu.v
`timescale 1ns/1ps

module main_tb;
    reg SW1, SW2, SW3, SW4;
    wire LD1, LD2;
    
    // Instantiate the main module
    main uut (
        .SW1(SW1),
        .SW2(SW2),
        .SW3(SW3),
        .SW4(SW4),
        .LD1(LD1),
        .LD2(LD2)
    );
    
    initial begin
        $dumpfile("t_main.vcd");
        $dumpvars(0, main_tb);
        
        // Test Full Adder (SW4 = 0)
        $display("Testing Full Adder (SW4=0)");
        SW4 = 0;
        
        // Test case 1: 0 + 0 + 0 = 00
        SW1 = 0; SW2 = 0; SW3 = 0;
        #10 $display("FA: %b + %b + %b = %b%b (LEDs: LD2=%b LD1=%b)", 
                     SW1, SW2, SW3, ~LD2, ~LD1, LD2, LD1);
        
        // Test case 2: 1 + 0 + 0 = 01
        SW1 = 1; SW2 = 0; SW3 = 0;
        #10 $display("FA: %b + %b + %b = %b%b (LEDs: LD2=%b LD1=%b)", 
                     SW1, SW2, SW3, ~LD2, ~LD1, LD2, LD1);
        
        // Test case 3: 1 + 1 + 0 = 10
        SW1 = 1; SW2 = 1; SW3 = 0;
        #10 $display("FA: %b + %b + %b = %b%b (LEDs: LD2=%b LD1=%b)", 
                     SW1, SW2, SW3, ~LD2, ~LD1, LD2, LD1);
        
        // Test case 4: 1 + 1 + 1 = 11
        SW1 = 1; SW2 = 1; SW3 = 1;
        #10 $display("FA: %b + %b + %b = %b%b (LEDs: LD2=%b LD1=%b)", 
                     SW1, SW2, SW3, ~LD2, ~LD1, LD2, LD1);
        
        // Test Full Subtractor (SW4 = 1)
        $display("\nTesting Full Subtractor (SW4=1)");
        SW4 = 1;
        // Test case 5: 0 - 0 - 0 = 00
        SW1 = 0; SW2 = 0; SW3 = 0;
        #10 $display("FS: %b - %b - %b = %b%b (LEDs: LD2=%b LD1=%b)", 
                     SW1, SW2, SW3, ~LD2, ~LD1, LD2, LD1);
        
        // Test case 6: 1 - 0 - 0 = 01
        SW1 = 1; SW2 = 0; SW3 = 0;
        #10 $display("FS: %b - %b - %b = %b%b (LEDs: LD2=%b LD1=%b)", 
                     SW1, SW2, SW3, ~LD2, ~LD1, LD2, LD1);
        
        // Test case 7: 1 - 1 - 0 = 00
        SW1 = 1; SW2 = 1; SW3 = 0;
        #10 $display("FS: %b - %b - %b = %b%b (LEDs: LD2=%b LD1=%b)", 
                     SW1, SW2, SW3, ~LD2, ~LD1, LD2, LD1);
        
        // Test case 8: 0 - 1 - 0 = 11 (borrow)
        SW1 = 0; SW2 = 1; SW3 = 0;
        #10 $display("FS: %b - %b - %b = %b%b (LEDs: LD2=%b LD1=%b)", 
                     SW1, SW2, SW3, ~LD2, ~LD1, LD2, LD1);
        
        #10 $finish;
    end
endmodule

syusekikairo/report/src/t_main.vcd
$date
	Tue Dec 09 15:44:58 2025
$end
$version
	Icarus Verilog
$end
$timescale
	1ps
$end
$scope module main_tb $end
$var wire 1 ! LD2 $end
$var wire 1 " LD1 $end
$var reg 1 # SW1 $end
$var reg 1 $ SW2 $end
$var reg 1 % SW3 $end
$var reg 1 & SW4 $end
$scope module uut $end
$var wire 1 # SW1 $end
$var wire 1 $ SW2 $end
$var wire 1 % SW3 $end
$var wire 1 & SW4 $end
$var wire 2 ' subResult [1:0] $end
$var wire 1 ( subD $end
$var wire 1 ) subB $end
$var wire 2 * muxResult [1:0] $end
$var wire 1 + addS $end
$var wire 2 , addResult [1:0] $end
$var wire 1 - addC $end
$var wire 1 ! LD2 $end
$var wire 1 " LD1 $end
$scope module FA $end
$var wire 1 # iA $end
$var wire 1 $ iB $end
$var wire 1 % iCy $end
$var wire 1 - oCy $end
$var wire 1 . s1 $end
$var wire 1 + oS $end
$var wire 1 / c2 $end
$var wire 1 0 c1 $end
$scope module HA1 $end
$var wire 1 # iA $end
$var wire 1 $ iB $end
$var wire 1 0 oC $end
$var wire 1 . oS $end
$upscope $end
$scope module HA2 $end
$var wire 1 . iA $end
$var wire 1 % iB $end
$var wire 1 / oC $end
$var wire 1 + oS $end
$upscope $end
$upscope $end
$scope module FS $end
$var wire 1 # iA $end
$var wire 1 $ iB $end
$var wire 1 % iBr $end
$var wire 1 ) oBr $end
$var wire 1 ( oD $end
$var wire 1 1 d1 $end
$var wire 1 2 b2 $end
$var wire 1 3 b1 $end
$scope module HS1 $end
$var wire 1 # iA $end
$var wire 1 $ iB $end
$var wire 1 3 oB $end
$var wire 1 1 oD $end
$upscope $end
$scope module HS2 $end
$var wire 1 1 iA $end
$var wire 1 % iB $end
$var wire 1 2 oB $end
$var wire 1 ( oD $end
$upscope $end
$upscope $end
$upscope $end
$upscope $end
$enddefinitions $end
$comment Show the parameter values. $end
$dumpall
$end
#0
$dumpvars
03
02
01
00
0/
0.
0-
b0 ,
0+
b0 *
0)
0(
b0 '
0&
0%
0$
0#
1"
1!
$end
#10000
0"
b1 *
b1 ,
1+
b1 '
1(
1.
11
1#
#20000
0!
1"
b10 *
0+
b10 ,
1-
b0 '
0(
0.
10
01
1$
#30000
0"
b11 *
1)
b11 ,
1+
b11 '
1(
12
1%
#40000
1!
1"
b0 *
0)
0-
b0 ,
0+
b0 '
0(
02
00
0%
0$
0#
1&
#50000
0"
b1 *
b1 ,
1+
b1 '
1(
1.
11
1#
#60000
1"
b0 *
0+
b10 ,
1-
b0 '
0(
0.
10
01
1$
#70000
0!
0"
b11 *
1)
1+
b1 ,
0-
b11 '
1(
13
1.
00
11
0#
